
{
  "response": {
  "version":"0.1",
  "termsofService":"http://www.wunderground.com/weather/api/d/terms.html",
  "features": {
  "history": 1
  }
	}
		,
	"history": {
		"date": {
		"pretty": "April 30, 2016",
		"year": "2016",
		"mon": "04",
		"mday": "30",
		"hour": "00",
		"min": "00",
		"tzname": "America/Montreal"
		},
		"utcdate": {
		"pretty": "April 30, 2016",
		"year": "2016",
		"mon": "04",
		"mday": "30",
		"hour": "04",
		"min": "00",
		"tzname": "UTC"
		},
		"observations": [
		{
		"date": {
		"pretty": "12:00 AM EDT on April 30, 2016",
		"year": "2016",
		"mon": "04",
		"mday": "30",
		"hour": "00",
		"min": "00",
		"tzname": "America/Montreal"
		},
		"utcdate": {
		"pretty": "4:00 AM GMT on April 30, 2016",
		"year": "2016",
		"mon": "04",
		"mday": "30",
		"hour": "04",
		"min": "00",
		"tzname": "UTC"
		},
		"tempm":"4.0", "tempi":"39.2","dewptm":"-7.0", "dewpti":"19.4","hum":"45","wspdm":"7.4", "wspdi":"4.6","wgustm":"-9999.0", "wgusti":"-9999.0","wdird":"350","wdire":"North","vism":"24.1", "visi":"15.0","pressurem":"1022.4", "pressurei":"30.19","windchillm":"2.1", "windchilli":"35.9","heatindexm":"-9999", "heatindexi":"-9999","precipm":"-9999.00", "precipi":"-9999.00","conds":"Scattered Clouds","icon":"partlycloudy","fog":"0","rain":"0","snow":"0","hail":"0","thunder":"0","tornado":"0","metar":"METAR CYUL 300400Z 35004KT 15SM SCT250 04/M07 A3018 RMK CI4 SLP224" },
		{
		"date": {
		"pretty": "1:00 AM EDT on April 30, 2016",
		"year": "2016",
		"mon": "04",
		"mday": "30",
		"hour": "01",
		"min": "00",
		"tzname": "America/Montreal"
		},
		"utcdate": {
		"pretty": "5:00 AM GMT on April 30, 2016",
		"year": "2016",
		"mon": "04",
		"mday": "30",
		"hour": "05",
		"min": "00",
		"tzname": "UTC"
		},
		"tempm":"3.0", "tempi":"37.4","dewptm":"-7.0", "dewpti":"19.4","hum":"48","wspdm":"13.0", "wspdi":"8.1","wgustm":"-9999.0", "wgusti":"-9999.0","wdird":"20","wdire":"NNE","vism":"24.1", "visi":"15.0","pressurem":"1022.8", "pressurei":"30.21","windchillm":"-0.3", "windchilli":"31.4","heatindexm":"-9999", "heatindexi":"-9999","precipm":"-9999.00", "precipi":"-9999.00","conds":"Scattered Clouds","icon":"partlycloudy","fog":"0","rain":"0","snow":"0","hail":"0","thunder":"0","tornado":"0","metar":"METAR CYUL 300500Z 02007KT 15SM SCT250 03/M07 A3020 RMK CI3 SLP228" },
		{
		"date": {
		"pretty": "2:00 AM EDT on April 30, 2016",
		"year": "2016",
		"mon": "04",
		"mday": "30",
		"hour": "02",
		"min": "00",
		"tzname": "America/Montreal"
		},
		"utcdate": {
		"pretty": "6:00 AM GMT on April 30, 2016",
		"year": "2016",
		"mon": "04",
		"mday": "30",
		"hour": "06",
		"min": "00",
		"tzname": "UTC"
		},
		"tempm":"4", "tempi":"40","dewptm":"-6", "dewpti":"21","hum":"32","wspdm":"9.3", "wspdi":"5.8","wgustm":"", "wgusti":"","wdird":"30","wdire":"NNE","vism":"24", "visi":"15","pressurem":"1023", "pressurei":"30.20","windchillm":"-999", "windchilli":"-999","heatindexm":"-9999", "heatindexi":"-9999","precipm":"", "precipi":"","conds":"Clear","icon":"clear","fog":"0","rain":"0","snow":"0","hail":"0","thunder":"0","tornado":"0","metar":"AAXX 30064 71627 13974 20305 10043 21063 30181 40226 50005 60001 80001 333 10116 21016 70000 555 10000 20000 33617 4019/" },
		{
		"date": {
		"pretty": "2:00 AM EDT on April 30, 2016",
		"year": "2016",
		"mon": "04",
		"mday": "30",
		"hour": "02",
		"min": "00",
		"tzname": "America/Montreal"
		},
		"utcdate": {
		"pretty": "6:00 AM GMT on April 30, 2016",
		"year": "2016",
		"mon": "04",
		"mday": "30",
		"hour": "06",
		"min": "00",
		"tzname": "UTC"
		},
		"tempm":"4.0", "tempi":"39.2","dewptm":"-6.0", "dewpti":"21.2","hum":"49","wspdm":"9.3", "wspdi":"5.8","wgustm":"-9999.0", "wgusti":"-9999.0","wdird":"30","wdire":"NNE","vism":"24.1", "visi":"15.0","pressurem":"1022.5", "pressurei":"30.20","windchillm":"1.7", "windchilli":"35.0","heatindexm":"-9999", "heatindexi":"-9999","precipm":"-9999.00", "precipi":"-9999.00","conds":"Partly Cloudy","icon":"partlycloudy","fog":"0","rain":"0","snow":"0","hail":"0","thunder":"0","tornado":"0","metar":"METAR CYUL 300600Z 03005KT 15SM FEW250 04/M06 A3019 RMK CI2 SLP225" },
		{
		"date": {
		"pretty": "3:00 AM EDT on April 30, 2016",
		"year": "2016",
		"mon": "04",
		"mday": "30",
		"hour": "03",
		"min": "00",
		"tzname": "America/Montreal"
		},
		"utcdate": {
		"pretty": "7:00 AM GMT on April 30, 2016",
		"year": "2016",
		"mon": "04",
		"mday": "30",
		"hour": "07",
		"min": "00",
		"tzname": "UTC"
		},
		"tempm":"3.0", "tempi":"37.4","dewptm":"-6.0", "dewpti":"21.2","hum":"52","wspdm":"11.1", "wspdi":"6.9","wgustm":"-9999.0", "wgusti":"-9999.0","wdird":"20","wdire":"NNE","vism":"24.1", "visi":"15.0","pressurem":"1023.2", "pressurei":"30.22","windchillm":"0.0", "windchilli":"32.1","heatindexm":"-9999", "heatindexi":"-9999","precipm":"-9999.00", "precipi":"-9999.00","conds":"Scattered Clouds","icon":"partlycloudy","fog":"0","rain":"0","snow":"0","hail":"0","thunder":"0","tornado":"0","metar":"METAR CYUL 300700Z 02006KT 15SM SCT240 03/M06 A3021 RMK CI4 SLP232" },
		{
		"date": {
		"pretty": "3:06 AM EDT on April 30, 2016",
		"year": "2016",
		"mon": "04",
		"mday": "30",
		"hour": "03",
		"min": "06",
		"tzname": "America/Montreal"
		},
		"utcdate": {
		"pretty": "7:06 AM GMT on April 30, 2016",
		"year": "2016",
		"mon": "04",
		"mday": "30",
		"hour": "07",
		"min": "06",
		"tzname": "UTC"
		},
		"tempm":"2.0", "tempi":"35.6","dewptm":"-6.0", "dewpti":"21.2","hum":"56","wspdm":"13.0", "wspdi":"8.1","wgustm":"-9999.0", "wgusti":"-9999.0","wdird":"30","wdire":"NNE","vism":"24.1", "visi":"15.0","pressurem":"1023.0", "pressurei":"30.21","windchillm":"-1.5", "windchilli":"29.2","heatindexm":"-9999", "heatindexi":"-9999","precipm":"-9999.00", "precipi":"-9999.00","conds":"Scattered Clouds","icon":"partlycloudy","fog":"0","rain":"0","snow":"0","hail":"0","thunder":"0","tornado":"0","metar":"SPECI CYUL 300706Z 03007KT 15SM SCT240 02/M06 A3020 RMK CI4 SLP230" },
		{
		"date": {
		"pretty": "4:00 AM EDT on April 30, 2016",
		"year": "2016",
		"mon": "04",
		"mday": "30",
		"hour": "04",
		"min": "00",
		"tzname": "America/Montreal"
		},
		"utcdate": {
		"pretty": "8:00 AM GMT on April 30, 2016",
		"year": "2016",
		"mon": "04",
		"mday": "30",
		"hour": "08",
		"min": "00",
		"tzname": "UTC"
		},
		"tempm":"3.0", "tempi":"37.4","dewptm":"-7.0", "dewpti":"19.4","hum":"48","wspdm":"16.7", "wspdi":"10.4","wgustm":"-9999.0", "wgusti":"-9999.0","wdird":"20","wdire":"NNE","vism":"24.1", "visi":"15.0","pressurem":"1023.1", "pressurei":"30.22","windchillm":"-1.0", "windchilli":"30.3","heatindexm":"-9999", "heatindexi":"-9999","precipm":"-9999.00", "precipi":"-9999.00","conds":"Partly Cloudy","icon":"partlycloudy","fog":"0","rain":"0","snow":"0","hail":"0","thunder":"0","tornado":"0","metar":"METAR CYUL 300800Z 02009KT 15SM FEW250 03/M07 A3021 RMK CI2 SLP231" },
		{
		"date": {
		"pretty": "4:05 AM EDT on April 30, 2016",
		"year": "2016",
		"mon": "04",
		"mday": "30",
		"hour": "04",
		"min": "05",
		"tzname": "America/Montreal"
		},
		"utcdate": {
		"pretty": "8:05 AM GMT on April 30, 2016",
		"year": "2016",
		"mon": "04",
		"mday": "30",
		"hour": "08",
		"min": "05",
		"tzname": "UTC"
		},
		"tempm":"2.0", "tempi":"35.6","dewptm":"-7.0", "dewpti":"19.4","hum":"52","wspdm":"16.7", "wspdi":"10.4","wgustm":"-9999.0", "wgusti":"-9999.0","wdird":"30","wdire":"NNE","vism":"24.1", "visi":"15.0","pressurem":"1023.1", "pressurei":"30.22","windchillm":"-2.2", "windchilli":"28.0","heatindexm":"-9999", "heatindexi":"-9999","precipm":"-9999.00", "precipi":"-9999.00","conds":"Partly Cloudy","icon":"partlycloudy","fog":"0","rain":"0","snow":"0","hail":"0","thunder":"0","tornado":"0","metar":"SPECI CYUL 300805Z 03009KT 15SM FEW250 02/M07 A3021 RMK CI2 SLP231" },
		{
		"date": {
		"pretty": "5:00 AM EDT on April 30, 2016",
		"year": "2016",
		"mon": "04",
		"mday": "30",
		"hour": "05",
		"min": "00",
		"tzname": "America/Montreal"
		},
		"utcdate": {
		"pretty": "9:00 AM GMT on April 30, 2016",
		"year": "2016",
		"mon": "04",
		"mday": "30",
		"hour": "09",
		"min": "00",
		"tzname": "UTC"
		},
		"tempm":"2.0", "tempi":"35.6","dewptm":"-7.0", "dewpti":"19.4","hum":"52","wspdm":"14.8", "wspdi":"9.2","wgustm":"-9999.0", "wgusti":"-9999.0","wdird":"20","wdire":"NNE","vism":"24.1", "visi":"15.0","pressurem":"1023.6", "pressurei":"30.23","windchillm":"-1.9", "windchilli":"28.6","heatindexm":"-9999", "heatindexi":"-9999","precipm":"-9999.00", "precipi":"-9999.00","conds":"Partly Cloudy","icon":"partlycloudy","fog":"0","rain":"0","snow":"0","hail":"0","thunder":"0","tornado":"0","metar":"METAR CYUL 300900Z 02008KT 15SM FEW250 02/M07 A3022 RMK CI1 CI TR SLP236" },
		{
		"date": {
		"pretty": "6:00 AM EDT on April 30, 2016",
		"year": "2016",
		"mon": "04",
		"mday": "30",
		"hour": "06",
		"min": "00",
		"tzname": "America/Montreal"
		},
		"utcdate": {
		"pretty": "10:00 AM GMT on April 30, 2016",
		"year": "2016",
		"mon": "04",
		"mday": "30",
		"hour": "10",
		"min": "00",
		"tzname": "UTC"
		},
		"tempm":"1.0", "tempi":"33.8","dewptm":"-8.0", "dewpti":"17.6","hum":"52","wspdm":"11.1", "wspdi":"6.9","wgustm":"-9999.0", "wgusti":"-9999.0","wdird":"20","wdire":"NNE","vism":"24.1", "visi":"15.0","pressurem":"1024.4", "pressurei":"30.25","windchillm":"-2.4", "windchilli":"27.7","heatindexm":"-9999", "heatindexi":"-9999","precipm":"-9999.00", "precipi":"-9999.00","conds":"Partly Cloudy","icon":"partlycloudy","fog":"0","rain":"0","snow":"0","hail":"0","thunder":"0","tornado":"0","metar":"METAR CYUL 301000Z 02006KT 15SM FEW250 01/M08 A3024 RMK CI1 CI TR SLP244" },
		{
		"date": {
		"pretty": "7:00 AM EDT on April 30, 2016",
		"year": "2016",
		"mon": "04",
		"mday": "30",
		"hour": "07",
		"min": "00",
		"tzname": "America/Montreal"
		},
		"utcdate": {
		"pretty": "11:00 AM GMT on April 30, 2016",
		"year": "2016",
		"mon": "04",
		"mday": "30",
		"hour": "11",
		"min": "00",
		"tzname": "UTC"
		},
		"tempm":"4.0", "tempi":"39.2","dewptm":"-7.0", "dewpti":"19.4","hum":"45","wspdm":"11.1", "wspdi":"6.9","wgustm":"-9999.0", "wgusti":"-9999.0","wdird":"30","wdire":"NNE","vism":"48.3", "visi":"30.0","pressurem":"1025.0", "pressurei":"30.27","windchillm":"1.2", "windchilli":"34.2","heatindexm":"-9999", "heatindexi":"-9999","precipm":"-9999.00", "precipi":"-9999.00","conds":"Partly Cloudy","icon":"partlycloudy","fog":"0","rain":"0","snow":"0","hail":"0","thunder":"0","tornado":"0","metar":"METAR CYUL 301100Z 03006KT 30SM FEW250 04/M07 A3026 RMK CI1 CI TR SLP250" },
		{
		"date": {
		"pretty": "8:00 AM EDT on April 30, 2016",
		"year": "2016",
		"mon": "04",
		"mday": "30",
		"hour": "08",
		"min": "00",
		"tzname": "America/Montreal"
		},
		"utcdate": {
		"pretty": "12:00 PM GMT on April 30, 2016",
		"year": "2016",
		"mon": "04",
		"mday": "30",
		"hour": "12",
		"min": "00",
		"tzname": "UTC"
		},
		"tempm":"6", "tempi":"42","dewptm":"-9", "dewpti":"16","hum":"21","wspdm":"22.2", "wspdi":"13.8","wgustm":"", "wgusti":"","wdird":"20","wdire":"NNE","vism":"45", "visi":"28","pressurem":"1026", "pressurei":"30.29","windchillm":"-999", "windchilli":"-999","heatindexm":"-9999", "heatindexi":"-9999","precipm":"", "precipi":"","conds":"Clear","icon":"clear","fog":"0","rain":"0","snow":"0","hail":"0","thunder":"0","tornado":"0","metar":"AAXX 30124 71627 13983 10212 10056 21091 30211 40256 52019 60001 80001 333 10116 20012 70000" },
		{
		"date": {
		"pretty": "8:00 AM EDT on April 30, 2016",
		"year": "2016",
		"mon": "04",
		"mday": "30",
		"hour": "08",
		"min": "00",
		"tzname": "America/Montreal"
		},
		"utcdate": {
		"pretty": "12:00 PM GMT on April 30, 2016",
		"year": "2016",
		"mon": "04",
		"mday": "30",
		"hour": "12",
		"min": "00",
		"tzname": "UTC"
		},
		"tempm":"6.0", "tempi":"42.8","dewptm":"-9.0", "dewpti":"15.8","hum":"34","wspdm":"25.9", "wspdi":"16.1","wgustm":"-9999.0", "wgusti":"-9999.0","wdird":"20","wdire":"NNE","vism":"48.3", "visi":"30.0","pressurem":"1025.5", "pressurei":"30.29","windchillm":"1.7", "windchilli":"35.1","heatindexm":"-9999", "heatindexi":"-9999","precipm":"-9999.00", "precipi":"-9999.00","conds":"Partly Cloudy","icon":"partlycloudy","fog":"0","rain":"0","snow":"0","hail":"0","thunder":"0","tornado":"0","metar":"METAR CYUL 301200Z 02014KT 30SM FEW250 06/M09 A3028 RMK CI1 CI TR SLP255" },
		{
		"date": {
		"pretty": "9:00 AM EDT on April 30, 2016",
		"year": "2016",
		"mon": "04",
		"mday": "30",
		"hour": "09",
		"min": "00",
		"tzname": "America/Montreal"
		},
		"utcdate": {
		"pretty": "1:00 PM GMT on April 30, 2016",
		"year": "2016",
		"mon": "04",
		"mday": "30",
		"hour": "13",
		"min": "00",
		"tzname": "UTC"
		},
		"tempm":"7.0", "tempi":"44.6","dewptm":"-9.0", "dewpti":"15.8","hum":"31","wspdm":"14.8", "wspdi":"9.2","wgustm":"-9999.0", "wgusti":"-9999.0","wdird":"360","wdire":"North","vism":"48.3", "visi":"30.0","pressurem":"1025.9", "pressurei":"30.30","windchillm":"4.3", "windchilli":"39.7","heatindexm":"-9999", "heatindexi":"-9999","precipm":"-9999.00", "precipi":"-9999.00","conds":"Partly Cloudy","icon":"partlycloudy","fog":"0","rain":"0","snow":"0","hail":"0","thunder":"0","tornado":"0","metar":"METAR CYUL 301300Z 36008KT 30SM FEW250 07/M09 A3029 RMK CI1 CI TR SLP259" },
		{
		"date": {
		"pretty": "10:00 AM EDT on April 30, 2016",
		"year": "2016",
		"mon": "04",
		"mday": "30",
		"hour": "10",
		"min": "00",
		"tzname": "America/Montreal"
		},
		"utcdate": {
		"pretty": "2:00 PM GMT on April 30, 2016",
		"year": "2016",
		"mon": "04",
		"mday": "30",
		"hour": "14",
		"min": "00",
		"tzname": "UTC"
		},
		"tempm":"9.0", "tempi":"48.2","dewptm":"-9.0", "dewpti":"15.8","hum":"27","wspdm":"13.0", "wspdi":"8.1","wgustm":"-9999.0", "wgusti":"-9999.0","wdird":"360","wdire":"North","vism":"48.3", "visi":"30.0","pressurem":"1026.0", "pressurei":"30.30","windchillm":"-999", "windchilli":"-999","heatindexm":"-9999", "heatindexi":"-9999","precipm":"-9999.00", "precipi":"-9999.00","conds":"Partly Cloudy","icon":"partlycloudy","fog":"0","rain":"0","snow":"0","hail":"0","thunder":"0","tornado":"0","metar":"METAR CYUL 301400Z 36007KT 340V050 30SM FEW250 09/M09 A3029 RMK CI1 CI TR SLP260" },
		{
		"date": {
		"pretty": "11:00 AM EDT on April 30, 2016",
		"year": "2016",
		"mon": "04",
		"mday": "30",
		"hour": "11",
		"min": "00",
		"tzname": "America/Montreal"
		},
		"utcdate": {
		"pretty": "3:00 PM GMT on April 30, 2016",
		"year": "2016",
		"mon": "04",
		"mday": "30",
		"hour": "15",
		"min": "00",
		"tzname": "UTC"
		},
		"tempm":"10.0", "tempi":"50.0","dewptm":"-9.0", "dewpti":"15.8","hum":"26","wspdm":"16.7", "wspdi":"10.4","wgustm":"-9999.0", "wgusti":"-9999.0","wdird":"360","wdire":"North","vism":"48.3", "visi":"30.0","pressurem":"1025.3", "pressurei":"30.28","windchillm":"-999", "windchilli":"-999","heatindexm":"-9999", "heatindexi":"-9999","precipm":"-9999.00", "precipi":"-9999.00","conds":"Clear","icon":"clear","fog":"0","rain":"0","snow":"0","hail":"0","thunder":"0","tornado":"0","metar":"METAR CYUL 301500Z 36009KT 30SM SKC 10/M09 A3027 RMK SLP253" },
		{
		"date": {
		"pretty": "12:00 PM EDT on April 30, 2016",
		"year": "2016",
		"mon": "04",
		"mday": "30",
		"hour": "12",
		"min": "00",
		"tzname": "America/Montreal"
		},
		"utcdate": {
		"pretty": "4:00 PM GMT on April 30, 2016",
		"year": "2016",
		"mon": "04",
		"mday": "30",
		"hour": "16",
		"min": "00",
		"tzname": "UTC"
		},
		"tempm":"11.0", "tempi":"51.8","dewptm":"-9.0", "dewpti":"15.8","hum":"24","wspdm":"7.4", "wspdi":"4.6","wgustm":"-9999.0", "wgusti":"-9999.0","wdird":"30","wdire":"NNE","vism":"48.3", "visi":"30.0","pressurem":"1025.1", "pressurei":"30.27","windchillm":"-999", "windchilli":"-999","heatindexm":"-9999", "heatindexi":"-9999","precipm":"-9999.00", "precipi":"-9999.00","conds":"Clear","icon":"clear","fog":"0","rain":"0","snow":"0","hail":"0","thunder":"0","tornado":"0","metar":"METAR CYUL 301600Z 03004KT 320V070 30SM SKC 11/M09 A3026 RMK SLP251" },
		{
		"date": {
		"pretty": "1:00 PM EDT on April 30, 2016",
		"year": "2016",
		"mon": "04",
		"mday": "30",
		"hour": "13",
		"min": "00",
		"tzname": "America/Montreal"
		},
		"utcdate": {
		"pretty": "5:00 PM GMT on April 30, 2016",
		"year": "2016",
		"mon": "04",
		"mday": "30",
		"hour": "17",
		"min": "00",
		"tzname": "UTC"
		},
		"tempm":"12.0", "tempi":"53.6","dewptm":"-9.0", "dewpti":"15.8","hum":"22","wspdm":"13.0", "wspdi":"8.1","wgustm":"29.6", "wgusti":"18.4","wdird":"350","wdire":"North","vism":"48.3", "visi":"30.0","pressurem":"1024.6", "pressurei":"30.26","windchillm":"-999", "windchilli":"-999","heatindexm":"-9999", "heatindexi":"-9999","precipm":"-9999.00", "precipi":"-9999.00","conds":"Clear","icon":"clear","fog":"0","rain":"0","snow":"0","hail":"0","thunder":"0","tornado":"0","metar":"METAR CYUL 301700Z 35007G16KT 310V030 30SM SKC 12/M09 A3025 RMK SLP246" },
		{
		"date": {
		"pretty": "2:00 PM EDT on April 30, 2016",
		"year": "2016",
		"mon": "04",
		"mday": "30",
		"hour": "14",
		"min": "00",
		"tzname": "America/Montreal"
		},
		"utcdate": {
		"pretty": "6:00 PM GMT on April 30, 2016",
		"year": "2016",
		"mon": "04",
		"mday": "30",
		"hour": "18",
		"min": "00",
		"tzname": "UTC"
		},
		"tempm":"13", "tempi":"56","dewptm":"-9", "dewpti":"15","hum":"10","wspdm":"13.0", "wspdi":"8.1","wgustm":"", "wgusti":"","wdird":"20","wdire":"NNE","vism":"45", "visi":"28","pressurem":"1024", "pressurei":"30.24","windchillm":"-999", "windchilli":"-999","heatindexm":"-9999", "heatindexi":"-9999","precipm":"", "precipi":"","conds":"Clear","icon":"clear","fog":"0","rain":"0","snow":"0","hail":"0","thunder":"0","tornado":"0","metar":"AAXX 30184 71627 13983 10207 10132 21093 30195 40240 58014 60001 80001 333 10137 20012 70000" },
		{
		"date": {
		"pretty": "2:00 PM EDT on April 30, 2016",
		"year": "2016",
		"mon": "04",
		"mday": "30",
		"hour": "14",
		"min": "00",
		"tzname": "America/Montreal"
		},
		"utcdate": {
		"pretty": "6:00 PM GMT on April 30, 2016",
		"year": "2016",
		"mon": "04",
		"mday": "30",
		"hour": "18",
		"min": "00",
		"tzname": "UTC"
		},
		"tempm":"13.0", "tempi":"55.4","dewptm":"-9.0", "dewpti":"15.8","hum":"21","wspdm":"14.8", "wspdi":"9.2","wgustm":"-9999.0", "wgusti":"-9999.0","wdird":"50","wdire":"NE","vism":"48.3", "visi":"30.0","pressurem":"1023.9", "pressurei":"30.24","windchillm":"-999", "windchilli":"-999","heatindexm":"-9999", "heatindexi":"-9999","precipm":"-9999.00", "precipi":"-9999.00","conds":"Partly Cloudy","icon":"partlycloudy","fog":"0","rain":"0","snow":"0","hail":"0","thunder":"0","tornado":"0","metar":"METAR CYUL 301800Z 05008KT 330V070 30SM FEW250 13/M09 A3023 RMK CI1 CI TR SLP239" },
		{
		"date": {
		"pretty": "3:00 PM EDT on April 30, 2016",
		"year": "2016",
		"mon": "04",
		"mday": "30",
		"hour": "15",
		"min": "00",
		"tzname": "America/Montreal"
		},
		"utcdate": {
		"pretty": "7:00 PM GMT on April 30, 2016",
		"year": "2016",
		"mon": "04",
		"mday": "30",
		"hour": "19",
		"min": "00",
		"tzname": "UTC"
		},
		"tempm":"14.0", "tempi":"57.2","dewptm":"-9.0", "dewpti":"15.8","hum":"20","wspdm":"7.4", "wspdi":"4.6","wgustm":"-9999.0", "wgusti":"-9999.0","wdird":"80","wdire":"East","vism":"48.3", "visi":"30.0","pressurem":"1023.4", "pressurei":"30.22","windchillm":"-999", "windchilli":"-999","heatindexm":"-9999", "heatindexi":"-9999","precipm":"-9999.00", "precipi":"-9999.00","conds":"Partly Cloudy","icon":"partlycloudy","fog":"0","rain":"0","snow":"0","hail":"0","thunder":"0","tornado":"0","metar":"METAR CYUL 301900Z 08004KT 350V110 30SM FEW250 14/M09 A3021 RMK CI1 CI TR SLP234" },
		{
		"date": {
		"pretty": "4:00 PM EDT on April 30, 2016",
		"year": "2016",
		"mon": "04",
		"mday": "30",
		"hour": "16",
		"min": "00",
		"tzname": "America/Montreal"
		},
		"utcdate": {
		"pretty": "8:00 PM GMT on April 30, 2016",
		"year": "2016",
		"mon": "04",
		"mday": "30",
		"hour": "20",
		"min": "00",
		"tzname": "UTC"
		},
		"tempm":"14.0", "tempi":"57.2","dewptm":"-8.0", "dewpti":"17.6","hum":"21","wspdm":"5.6", "wspdi":"3.5","wgustm":"-9999.0", "wgusti":"-9999.0","wdird":"90","wdire":"East","vism":"48.3", "visi":"30.0","pressurem":"1023.1", "pressurei":"30.22","windchillm":"-999", "windchilli":"-999","heatindexm":"-9999", "heatindexi":"-9999","precipm":"-9999.00", "precipi":"-9999.00","conds":"Partly Cloudy","icon":"partlycloudy","fog":"0","rain":"0","snow":"0","hail":"0","thunder":"0","tornado":"0","metar":"METAR CYUL 302000Z 09003KT 350V110 30SM FEW250 14/M08 A3021 RMK CI1 SLP231" },
		{
		"date": {
		"pretty": "5:00 PM EDT on April 30, 2016",
		"year": "2016",
		"mon": "04",
		"mday": "30",
		"hour": "17",
		"min": "00",
		"tzname": "America/Montreal"
		},
		"utcdate": {
		"pretty": "9:00 PM GMT on April 30, 2016",
		"year": "2016",
		"mon": "04",
		"mday": "30",
		"hour": "21",
		"min": "00",
		"tzname": "UTC"
		},
		"tempm":"15.0", "tempi":"59.0","dewptm":"-9.0", "dewpti":"15.8","hum":"19","wspdm":"13.0", "wspdi":"8.1","wgustm":"-9999.0", "wgusti":"-9999.0","wdird":"110","wdire":"ESE","vism":"48.3", "visi":"30.0","pressurem":"1023.0", "pressurei":"30.21","windchillm":"-999", "windchilli":"-999","heatindexm":"-9999", "heatindexi":"-9999","precipm":"-9999.00", "precipi":"-9999.00","conds":"Scattered Clouds","icon":"partlycloudy","fog":"0","rain":"0","snow":"0","hail":"0","thunder":"0","tornado":"0","metar":"METAR CYUL 302100Z 11007KT 030V180 30SM SCT250 15/M09 A3020 RMK CI3 SLP230" },
		{
		"date": {
		"pretty": "6:00 PM EDT on April 30, 2016",
		"year": "2016",
		"mon": "04",
		"mday": "30",
		"hour": "18",
		"min": "00",
		"tzname": "America/Montreal"
		},
		"utcdate": {
		"pretty": "10:00 PM GMT on April 30, 2016",
		"year": "2016",
		"mon": "04",
		"mday": "30",
		"hour": "22",
		"min": "00",
		"tzname": "UTC"
		},
		"tempm":"15.0", "tempi":"59.0","dewptm":"-9.0", "dewpti":"15.8","hum":"19","wspdm":"13.0", "wspdi":"8.1","wgustm":"-9999.0", "wgusti":"-9999.0","wdird":"90","wdire":"East","vism":"48.3", "visi":"30.0","pressurem":"1022.7", "pressurei":"30.20","windchillm":"-999", "windchilli":"-999","heatindexm":"-9999", "heatindexi":"-9999","precipm":"-9999.00", "precipi":"-9999.00","conds":"Partly Cloudy","icon":"partlycloudy","fog":"0","rain":"0","snow":"0","hail":"0","thunder":"0","tornado":"0","metar":"METAR CYUL 302200Z 09007KT 360V100 30SM FEW250 15/M09 A3019 RMK CI1 SLP227" },
		{
		"date": {
		"pretty": "7:00 PM EDT on April 30, 2016",
		"year": "2016",
		"mon": "04",
		"mday": "30",
		"hour": "19",
		"min": "00",
		"tzname": "America/Montreal"
		},
		"utcdate": {
		"pretty": "11:00 PM GMT on April 30, 2016",
		"year": "2016",
		"mon": "04",
		"mday": "30",
		"hour": "23",
		"min": "00",
		"tzname": "UTC"
		},
		"tempm":"14.0", "tempi":"57.2","dewptm":"-9.0", "dewpti":"15.8","hum":"20","wspdm":"13.0", "wspdi":"8.1","wgustm":"-9999.0", "wgusti":"-9999.0","wdird":"150","wdire":"SSE","vism":"48.3", "visi":"30.0","pressurem":"1022.8", "pressurei":"30.21","windchillm":"-999", "windchilli":"-999","heatindexm":"-9999", "heatindexi":"-9999","precipm":"-9999.00", "precipi":"-9999.00","conds":"Partly Cloudy","icon":"partlycloudy","fog":"0","rain":"0","snow":"0","hail":"0","thunder":"0","tornado":"0","metar":"METAR CYUL 302300Z 15007KT 090V160 30SM FEW220 FEW250 14/M09 A3020 RMK CC1CI2 CC TR SLP228" },
		{
		"date": {
		"pretty": "8:00 PM EDT on April 30, 2016",
		"year": "2016",
		"mon": "04",
		"mday": "30",
		"hour": "20",
		"min": "00",
		"tzname": "America/Montreal"
		},
		"utcdate": {
		"pretty": "12:00 AM GMT on May 01, 2016",
		"year": "2016",
		"mon": "05",
		"mday": "01",
		"hour": "00",
		"min": "00",
		"tzname": "UTC"
		},
		"tempm":"13", "tempi":"55","dewptm":"-9", "dewpti":"15","hum":"10","wspdm":"13.0", "wspdi":"8.1","wgustm":"", "wgusti":"","wdird":"110","wdire":"ESE","vism":"45", "visi":"28","pressurem":"1023", "pressurei":"30.21","windchillm":"-999", "windchilli":"-999","heatindexm":"-9999", "heatindexi":"-9999","precipm":"", "precipi":"","conds":"Clear","icon":"clear","fog":"0","rain":"0","snow":"0","hail":"0","thunder":"0","tornado":"0","metar":"AAXX 01004 71627 13983 71107 10130 21094 30185 40229 55001 60001 80004 333 10151 20012 70000" },
		{
		"date": {
		"pretty": "8:00 PM EDT on April 30, 2016",
		"year": "2016",
		"mon": "04",
		"mday": "30",
		"hour": "20",
		"min": "00",
		"tzname": "America/Montreal"
		},
		"utcdate": {
		"pretty": "12:00 AM GMT on May 01, 2016",
		"year": "2016",
		"mon": "05",
		"mday": "01",
		"hour": "00",
		"min": "00",
		"tzname": "UTC"
		},
		"tempm":"13.0", "tempi":"55.4","dewptm":"-9.0", "dewpti":"15.8","hum":"21","wspdm":"11.1", "wspdi":"6.9","wgustm":"-9999.0", "wgusti":"-9999.0","wdird":"100","wdire":"East","vism":"48.3", "visi":"30.0","pressurem":"1022.9", "pressurei":"30.21","windchillm":"-999", "windchilli":"-999","heatindexm":"-9999", "heatindexi":"-9999","precipm":"-9999.00", "precipi":"-9999.00","conds":"Mostly Cloudy","icon":"mostlycloudy","fog":"0","rain":"0","snow":"0","hail":"0","thunder":"0","tornado":"0","metar":"METAR CYUL 010000Z 10006KT 30SM SCT250 BKN280 13/M09 A3020 RMK CI4CI3 SLP229" },
		{
		"date": {
		"pretty": "9:00 PM EDT on April 30, 2016",
		"year": "2016",
		"mon": "04",
		"mday": "30",
		"hour": "21",
		"min": "00",
		"tzname": "America/Montreal"
		},
		"utcdate": {
		"pretty": "1:00 AM GMT on May 01, 2016",
		"year": "2016",
		"mon": "05",
		"mday": "01",
		"hour": "01",
		"min": "00",
		"tzname": "UTC"
		},
		"tempm":"12.0", "tempi":"53.6","dewptm":"-10.0", "dewpti":"14.0","hum":"21","wspdm":"11.1", "wspdi":"6.9","wgustm":"-9999.0", "wgusti":"-9999.0","wdird":"100","wdire":"East","vism":"24.1", "visi":"15.0","pressurem":"1023.5", "pressurei":"30.23","windchillm":"-999", "windchilli":"-999","heatindexm":"-9999", "heatindexi":"-9999","precipm":"-9999.00", "precipi":"-9999.00","conds":"Mostly Cloudy","icon":"mostlycloudy","fog":"0","rain":"0","snow":"0","hail":"0","thunder":"0","tornado":"0","metar":"METAR CYUL 010100Z 10006KT 15SM BKN250 12/M10 A3022 RMK CI5 SLP235" },
		{
		"date": {
		"pretty": "10:00 PM EDT on April 30, 2016",
		"year": "2016",
		"mon": "04",
		"mday": "30",
		"hour": "22",
		"min": "00",
		"tzname": "America/Montreal"
		},
		"utcdate": {
		"pretty": "2:00 AM GMT on May 01, 2016",
		"year": "2016",
		"mon": "05",
		"mday": "01",
		"hour": "02",
		"min": "00",
		"tzname": "UTC"
		},
		"tempm":"11.0", "tempi":"51.8","dewptm":"-9.0", "dewpti":"15.8","hum":"24","wspdm":"7.4", "wspdi":"4.6","wgustm":"-9999.0", "wgusti":"-9999.0","wdird":"70","wdire":"ENE","vism":"24.1", "visi":"15.0","pressurem":"1023.5", "pressurei":"30.23","windchillm":"-999", "windchilli":"-999","heatindexm":"-9999", "heatindexi":"-9999","precipm":"-9999.00", "precipi":"-9999.00","conds":"Scattered Clouds","icon":"partlycloudy","fog":"0","rain":"0","snow":"0","hail":"0","thunder":"0","tornado":"0","metar":"METAR CYUL 010200Z 07004KT 15SM SCT250 11/M09 A3022 RMK CI3 SLP235" },
		{
		"date": {
		"pretty": "11:00 PM EDT on April 30, 2016",
		"year": "2016",
		"mon": "04",
		"mday": "30",
		"hour": "23",
		"min": "00",
		"tzname": "America/Montreal"
		},
		"utcdate": {
		"pretty": "3:00 AM GMT on May 01, 2016",
		"year": "2016",
		"mon": "05",
		"mday": "01",
		"hour": "03",
		"min": "00",
		"tzname": "UTC"
		},
		"tempm":"10.0", "tempi":"50.0","dewptm":"-10.0", "dewpti":"14.0","hum":"24","wspdm":"11.1", "wspdi":"6.9","wgustm":"-9999.0", "wgusti":"-9999.0","wdird":"50","wdire":"NE","vism":"24.1", "visi":"15.0","pressurem":"1023.0", "pressurei":"30.21","windchillm":"-999", "windchilli":"-999","heatindexm":"-9999", "heatindexi":"-9999","precipm":"-9999.00", "precipi":"-9999.00","conds":"Mostly Cloudy","icon":"mostlycloudy","fog":"0","rain":"0","snow":"0","hail":"0","thunder":"0","tornado":"0","metar":"METAR CYUL 010300Z 05006KT 15SM BKN250 10/M10 A3020 RMK CI5 SLP230" }
		],
		"dailysummary": [
		{ "date": {
		"pretty": "12:00 AM EDT on April 30, 2016",
		"year": "2016",
		"mon": "04",
		"mday": "30",
		"hour": "00",
		"min": "00",
		"tzname": "America/Montreal"
		},
		"fog":"0","rain":"0","snow":"0","snowfallm":"", "snowfalli":"","monthtodatesnowfallm":"", "monthtodatesnowfalli":"","since1julsnowfallm":"", "since1julsnowfalli":"","snowdepthm":"", "snowdepthi":"","hail":"0","thunder":"0","tornado":"0","meantempm":"8", "meantempi":"46","meandewptm":"-8", "meandewpti":"17","meanpressurem":"1023.78", "meanpressurei":"30.23","meanwindspdm":"11", "meanwindspdi":"7","meanwdire":"NE","meanwdird":"41","meanvism":"24.1", "meanvisi":"15.0","humidity":"32","maxtempm":"15", "maxtempi":"59","mintempm":"1", "mintempi":"34","maxhumidity":"56","minhumidity":"10","maxdewptm":"-6", "maxdewpti":"21","mindewptm":"-10", "mindewpti":"14","maxpressurem":"1026", "maxpressurei":"30.30","minpressurem":"1022", "minpressurei":"30.19","maxwspdm":"26", "maxwspdi":"16","minwspdm":"6", "minwspdi":"4","maxvism":"24.1", "maxvisi":"15.0","minvism":"24.1", "minvisi":"15.0","gdegreedays":"0","heatingdegreedays":"18","coolingdegreedays":"0","precipm":"0.0", "precipi":"0.00","precipsource":"3Or6HourObs","heatingdegreedaysnormal":"","monthtodateheatingdegreedays":"","monthtodateheatingdegreedaysnormal":"","since1sepheatingdegreedays":"","since1sepheatingdegreedaysnormal":"","since1julheatingdegreedays":"","since1julheatingdegreedaysnormal":"","coolingdegreedaysnormal":"","monthtodatecoolingdegreedays":"","monthtodatecoolingdegreedaysnormal":"","since1sepcoolingdegreedays":"","since1sepcoolingdegreedaysnormal":"","since1jancoolingdegreedays":"","since1jancoolingdegreedaysnormal":"" }
		]
	}
}
