
{
  "response": {
  "version":"0.1",
  "termsofService":"http://www.wunderground.com/weather/api/d/terms.html",
  "features": {
  "history": 1
  }
	}
		,
	"history": {
		"date": {
		"pretty": "July 19, 2017",
		"year": "2017",
		"mon": "07",
		"mday": "19",
		"hour": "00",
		"min": "00",
		"tzname": "America/Montreal"
		},
		"utcdate": {
		"pretty": "July 19, 2017",
		"year": "2017",
		"mon": "07",
		"mday": "19",
		"hour": "04",
		"min": "00",
		"tzname": "UTC"
		},
		"observations": [
		{
		"date": {
		"pretty": "12:00 AM EDT on July 19, 2017",
		"year": "2017",
		"mon": "07",
		"mday": "19",
		"hour": "00",
		"min": "00",
		"tzname": "America/Montreal"
		},
		"utcdate": {
		"pretty": "4:00 AM GMT on July 19, 2017",
		"year": "2017",
		"mon": "07",
		"mday": "19",
		"hour": "04",
		"min": "00",
		"tzname": "UTC"
		},
		"tempm":"22.5", "tempi":"72.5","dewptm":"18.3", "dewpti":"64.9","hum":"77","wspdm":"1.9", "wspdi":"1.2","wgustm":"-9999.0", "wgusti":"-9999.0","wdird":"240","wdire":"WSW","vism":"-9999.0", "visi":"-9999.0","pressurem":"1016.2", "pressurei":"30.01","windchillm":"-999", "windchilli":"-999","heatindexm":"-9999", "heatindexi":"-9999","precipm":"-9999.00", "precipi":"-9999.00","conds":"Unknown","icon":"unknown","fog":"0","rain":"0","snow":"0","hail":"0","thunder":"0","tornado":"0","metar":"METAR CWTA 190400Z AUTO 24001KT 23/18 RMK AO1 SLP162 T02250183 51002" },
		{
		"date": {
		"pretty": "1:00 AM EDT on July 19, 2017",
		"year": "2017",
		"mon": "07",
		"mday": "19",
		"hour": "01",
		"min": "00",
		"tzname": "America/Montreal"
		},
		"utcdate": {
		"pretty": "5:00 AM GMT on July 19, 2017",
		"year": "2017",
		"mon": "07",
		"mday": "19",
		"hour": "05",
		"min": "00",
		"tzname": "UTC"
		},
		"tempm":"23.1", "tempi":"73.6","dewptm":"18.2", "dewpti":"64.8","hum":"74","wspdm":"5.6", "wspdi":"3.5","wgustm":"-9999.0", "wgusti":"-9999.0","wdird":"260","wdire":"West","vism":"-9999.0", "visi":"-9999.0","pressurem":"1015.9", "pressurei":"30.00","windchillm":"-999", "windchilli":"-999","heatindexm":"-9999", "heatindexi":"-9999","precipm":"-9999.00", "precipi":"-9999.00","conds":"Unknown","icon":"unknown","fog":"0","rain":"0","snow":"0","hail":"0","thunder":"0","tornado":"0","metar":"METAR CWTA 190500Z AUTO 26003KT 23/18 RMK AO1 SLP159 T02310182 58002" },
		{
		"date": {
		"pretty": "2:00 AM EDT on July 19, 2017",
		"year": "2017",
		"mon": "07",
		"mday": "19",
		"hour": "02",
		"min": "00",
		"tzname": "America/Montreal"
		},
		"utcdate": {
		"pretty": "6:00 AM GMT on July 19, 2017",
		"year": "2017",
		"mon": "07",
		"mday": "19",
		"hour": "06",
		"min": "00",
		"tzname": "UTC"
		},
		"tempm":"22", "tempi":"72","dewptm":"18", "dewpti":"65","hum":"72","wspdm":"5.6", "wspdi":"3.5","wgustm":"", "wgusti":"","wdird":"200","wdire":"SSW","vism":"", "visi":"","pressurem":"1016", "pressurei":"29.99","windchillm":"-999", "windchilli":"-999","heatindexm":"-9999", "heatindexi":"-9999","precipm":"", "precipi":"","conds":"","icon":"","fog":"0","rain":"0","snow":"0","hail":"0","thunder":"0","tornado":"0","metar":"AAXX 19064 71612 16/// /2003 10223 20182 30068 40155 58007 60001 333 10291 20173 70000" },
		{
		"date": {
		"pretty": "3:00 AM EDT on July 19, 2017",
		"year": "2017",
		"mon": "07",
		"mday": "19",
		"hour": "03",
		"min": "00",
		"tzname": "America/Montreal"
		},
		"utcdate": {
		"pretty": "7:00 AM GMT on July 19, 2017",
		"year": "2017",
		"mon": "07",
		"mday": "19",
		"hour": "07",
		"min": "00",
		"tzname": "UTC"
		},
		"tempm":"21.4", "tempi":"70.5","dewptm":"17.9", "dewpti":"64.2","hum":"80","wspdm":"3.7", "wspdi":"2.3","wgustm":"-9999.0", "wgusti":"-9999.0","wdird":"210","wdire":"SSW","vism":"-9999.0", "visi":"-9999.0","pressurem":"1015.2", "pressurei":"29.98","windchillm":"-999", "windchilli":"-999","heatindexm":"-9999", "heatindexi":"-9999","precipm":"-9999.00", "precipi":"-9999.00","conds":"Unknown","icon":"unknown","fog":"0","rain":"0","snow":"0","hail":"0","thunder":"0","tornado":"0","metar":"METAR CWTA 190700Z AUTO 21002KT 21/18 RMK AO1 SLP152 T02140179 57010" },
		{
		"date": {
		"pretty": "4:00 AM EDT on July 19, 2017",
		"year": "2017",
		"mon": "07",
		"mday": "19",
		"hour": "04",
		"min": "00",
		"tzname": "America/Montreal"
		},
		"utcdate": {
		"pretty": "8:00 AM GMT on July 19, 2017",
		"year": "2017",
		"mon": "07",
		"mday": "19",
		"hour": "08",
		"min": "00",
		"tzname": "UTC"
		},
		"tempm":"20.9", "tempi":"69.6","dewptm":"17.3", "dewpti":"63.1","hum":"80","wspdm":"3.7", "wspdi":"2.3","wgustm":"-9999.0", "wgusti":"-9999.0","wdird":"240","wdire":"WSW","vism":"-9999.0", "visi":"-9999.0","pressurem":"1014.9", "pressurei":"29.97","windchillm":"-999", "windchilli":"-999","heatindexm":"-9999", "heatindexi":"-9999","precipm":"-9999.00", "precipi":"-9999.00","conds":"Unknown","icon":"unknown","fog":"0","rain":"0","snow":"0","hail":"0","thunder":"0","tornado":"0","metar":"METAR CWTA 190800Z AUTO 24002KT 21/17 RMK AO1 SLP149 T02090173 56010" },
		{
		"date": {
		"pretty": "5:00 AM EDT on July 19, 2017",
		"year": "2017",
		"mon": "07",
		"mday": "19",
		"hour": "05",
		"min": "00",
		"tzname": "America/Montreal"
		},
		"utcdate": {
		"pretty": "9:00 AM GMT on July 19, 2017",
		"year": "2017",
		"mon": "07",
		"mday": "19",
		"hour": "09",
		"min": "00",
		"tzname": "UTC"
		},
		"tempm":"21", "tempi":"69","dewptm":"17", "dewpti":"63","hum":"75","wspdm":"7.4", "wspdi":"4.6","wgustm":"", "wgusti":"","wdird":"250","wdire":"WSW","vism":"", "visi":"","pressurem":"1015", "pressurei":"29.97","windchillm":"-999", "windchilli":"-999","heatindexm":"-9999", "heatindexi":"-9999","precipm":"", "precipi":"","conds":"","icon":"","fog":"0","rain":"0","snow":"0","hail":"0","thunder":"0","tornado":"0","metar":"AAXX 19094 71612 26/// /2504 10208 20171 30062 40149 56006 333 60007" },
		{
		"date": {
		"pretty": "5:00 AM EDT on July 19, 2017",
		"year": "2017",
		"mon": "07",
		"mday": "19",
		"hour": "05",
		"min": "00",
		"tzname": "America/Montreal"
		},
		"utcdate": {
		"pretty": "9:00 AM GMT on July 19, 2017",
		"year": "2017",
		"mon": "07",
		"mday": "19",
		"hour": "09",
		"min": "00",
		"tzname": "UTC"
		},
		"tempm":"20.8", "tempi":"69.4","dewptm":"17.1", "dewpti":"62.8","hum":"79","wspdm":"7.4", "wspdi":"4.6","wgustm":"-9999.0", "wgusti":"-9999.0","wdird":"250","wdire":"WSW","vism":"-9999.0", "visi":"-9999.0","pressurem":"1014.9", "pressurei":"29.97","windchillm":"-999", "windchilli":"-999","heatindexm":"-9999", "heatindexi":"-9999","precipm":"-9999.00", "precipi":"-9999.00","conds":"Unknown","icon":"unknown","fog":"0","rain":"0","snow":"0","hail":"0","thunder":"0","tornado":"0","metar":"METAR CWTA 190900Z AUTO 25004KT 21/17 RMK AO1 SLP149 T02080171 56006" },
		{
		"date": {
		"pretty": "7:00 AM EDT on July 19, 2017",
		"year": "2017",
		"mon": "07",
		"mday": "19",
		"hour": "07",
		"min": "00",
		"tzname": "America/Montreal"
		},
		"utcdate": {
		"pretty": "11:00 AM GMT on July 19, 2017",
		"year": "2017",
		"mon": "07",
		"mday": "19",
		"hour": "11",
		"min": "00",
		"tzname": "UTC"
		},
		"tempm":"21.0", "tempi":"69.8","dewptm":"16.7", "dewpti":"62.1","hum":"76","wspdm":"7.4", "wspdi":"4.6","wgustm":"-9999.0", "wgusti":"-9999.0","wdird":"210","wdire":"SSW","vism":"-9999.0", "visi":"-9999.0","pressurem":"1015.0", "pressurei":"29.98","windchillm":"-999", "windchilli":"-999","heatindexm":"-9999", "heatindexi":"-9999","precipm":"-9999.00", "precipi":"-9999.00","conds":"Unknown","icon":"unknown","fog":"0","rain":"0","snow":"0","hail":"0","thunder":"0","tornado":"0","metar":"METAR CWTA 191100Z AUTO 21004KT 21/17 RMK AO1 SLP150 T02100167 53001" },
		{
		"date": {
		"pretty": "8:00 AM EDT on July 19, 2017",
		"year": "2017",
		"mon": "07",
		"mday": "19",
		"hour": "08",
		"min": "00",
		"tzname": "America/Montreal"
		},
		"utcdate": {
		"pretty": "12:00 PM GMT on July 19, 2017",
		"year": "2017",
		"mon": "07",
		"mday": "19",
		"hour": "12",
		"min": "00",
		"tzname": "UTC"
		},
		"tempm":"22", "tempi":"72","dewptm":"17", "dewpti":"62","hum":"64","wspdm":"5.6", "wspdi":"3.5","wgustm":"", "wgusti":"","wdird":"230","wdire":"SW","vism":"", "visi":"","pressurem":"1015", "pressurei":"29.98","windchillm":"-999", "windchilli":"-999","heatindexm":"-9999", "heatindexi":"-9999","precipm":"", "precipi":"","conds":"","icon":"","fog":"0","rain":"0","snow":"0","hail":"0","thunder":"0","tornado":"0","metar":"AAXX 19124 71612 16/// /2303 10221 20169 30065 40152 53003 60001 333 10291 20204 70000" },
		{
		"date": {
		"pretty": "8:00 AM EDT on July 19, 2017",
		"year": "2017",
		"mon": "07",
		"mday": "19",
		"hour": "08",
		"min": "00",
		"tzname": "America/Montreal"
		},
		"utcdate": {
		"pretty": "12:00 PM GMT on July 19, 2017",
		"year": "2017",
		"mon": "07",
		"mday": "19",
		"hour": "12",
		"min": "00",
		"tzname": "UTC"
		},
		"tempm":"22.1", "tempi":"71.8","dewptm":"16.9", "dewpti":"62.4","hum":"72","wspdm":"5.6", "wspdi":"3.5","wgustm":"-9999.0", "wgusti":"-9999.0","wdird":"230","wdire":"SW","vism":"-9999.0", "visi":"-9999.0","pressurem":"1015.2", "pressurei":"29.98","windchillm":"-999", "windchilli":"-999","heatindexm":"-9999", "heatindexi":"-9999","precipm":"-9999.00", "precipi":"-9999.00","conds":"Unknown","icon":"unknown","fog":"0","rain":"0","snow":"0","hail":"0","thunder":"0","tornado":"0","metar":"METAR CWTA 191200Z AUTO 23003KT 22/17 RMK AO1 SLP152 T02210169 53003" },
		{
		"date": {
		"pretty": "9:00 AM EDT on July 19, 2017",
		"year": "2017",
		"mon": "07",
		"mday": "19",
		"hour": "09",
		"min": "00",
		"tzname": "America/Montreal"
		},
		"utcdate": {
		"pretty": "1:00 PM GMT on July 19, 2017",
		"year": "2017",
		"mon": "07",
		"mday": "19",
		"hour": "13",
		"min": "00",
		"tzname": "UTC"
		},
		"tempm":"23.1", "tempi":"73.6","dewptm":"17.3", "dewpti":"63.1","hum":"70","wspdm":"7.4", "wspdi":"4.6","wgustm":"-9999.0", "wgusti":"-9999.0","wdird":"260","wdire":"West","vism":"-9999.0", "visi":"-9999.0","pressurem":"1015.1", "pressurei":"29.98","windchillm":"-999", "windchilli":"-999","heatindexm":"-9999", "heatindexi":"-9999","precipm":"-9999.00", "precipi":"-9999.00","conds":"Unknown","icon":"unknown","fog":"0","rain":"0","snow":"0","hail":"0","thunder":"0","tornado":"0","metar":"METAR CWTA 191300Z AUTO 26004KT 23/17 RMK AO1 SLP151 T02310173 50004" },
		{
		"date": {
		"pretty": "10:00 AM EDT on July 19, 2017",
		"year": "2017",
		"mon": "07",
		"mday": "19",
		"hour": "10",
		"min": "00",
		"tzname": "America/Montreal"
		},
		"utcdate": {
		"pretty": "2:00 PM GMT on July 19, 2017",
		"year": "2017",
		"mon": "07",
		"mday": "19",
		"hour": "14",
		"min": "00",
		"tzname": "UTC"
		},
		"tempm":"24.5", "tempi":"76.1","dewptm":"17.8", "dewpti":"64.0","hum":"66","wspdm":"7.4", "wspdi":"4.6","wgustm":"-9999.0", "wgusti":"-9999.0","wdird":"210","wdire":"SSW","vism":"-9999.0", "visi":"-9999.0","pressurem":"1015.1", "pressurei":"29.98","windchillm":"-999", "windchilli":"-999","heatindexm":"-9999", "heatindexi":"-9999","precipm":"-9999.00", "precipi":"-9999.00","conds":"Unknown","icon":"unknown","fog":"0","rain":"0","snow":"0","hail":"0","thunder":"0","tornado":"0","metar":"METAR CWTA 191400Z AUTO 21004KT 25/18 RMK AO1 SLP151 T02450178 51001" },
		{
		"date": {
		"pretty": "11:00 AM EDT on July 19, 2017",
		"year": "2017",
		"mon": "07",
		"mday": "19",
		"hour": "11",
		"min": "00",
		"tzname": "America/Montreal"
		},
		"utcdate": {
		"pretty": "3:00 PM GMT on July 19, 2017",
		"year": "2017",
		"mon": "07",
		"mday": "19",
		"hour": "15",
		"min": "00",
		"tzname": "UTC"
		},
		"tempm":"26", "tempi":"78","dewptm":"18", "dewpti":"64","hum":"53","wspdm":"5.6", "wspdi":"3.5","wgustm":"", "wgusti":"","wdird":"200","wdire":"SSW","vism":"", "visi":"","pressurem":"1015", "pressurei":"29.96","windchillm":"-999", "windchilli":"-999","heatindexm":"-9999", "heatindexi":"-9999","precipm":"", "precipi":"","conds":"","icon":"","fog":"0","rain":"0","snow":"0","hail":"0","thunder":"0","tornado":"0","metar":"AAXX 19154 71612 26/// /2003 10258 20177 30059 40146 58006 333 60007" },
		{
		"date": {
		"pretty": "11:00 AM EDT on July 19, 2017",
		"year": "2017",
		"mon": "07",
		"mday": "19",
		"hour": "11",
		"min": "00",
		"tzname": "America/Montreal"
		},
		"utcdate": {
		"pretty": "3:00 PM GMT on July 19, 2017",
		"year": "2017",
		"mon": "07",
		"mday": "19",
		"hour": "15",
		"min": "00",
		"tzname": "UTC"
		},
		"tempm":"25.8", "tempi":"78.4","dewptm":"17.7", "dewpti":"63.9","hum":"61","wspdm":"5.6", "wspdi":"3.5","wgustm":"-9999.0", "wgusti":"-9999.0","wdird":"200","wdire":"SSW","vism":"-9999.0", "visi":"-9999.0","pressurem":"1014.6", "pressurei":"29.96","windchillm":"-999", "windchilli":"-999","heatindexm":"-9999", "heatindexi":"-9999","precipm":"-9999.00", "precipi":"-9999.00","conds":"Unknown","icon":"unknown","fog":"0","rain":"0","snow":"0","hail":"0","thunder":"0","tornado":"0","metar":"METAR CWTA 191500Z AUTO 20003KT 26/18 RMK AO1 SLP146 T02580177 58006" },
		{
		"date": {
		"pretty": "12:00 PM EDT on July 19, 2017",
		"year": "2017",
		"mon": "07",
		"mday": "19",
		"hour": "12",
		"min": "00",
		"tzname": "America/Montreal"
		},
		"utcdate": {
		"pretty": "4:00 PM GMT on July 19, 2017",
		"year": "2017",
		"mon": "07",
		"mday": "19",
		"hour": "16",
		"min": "00",
		"tzname": "UTC"
		},
		"tempm":"26.2", "tempi":"79.2","dewptm":"17.5", "dewpti":"63.5","hum":"59","wspdm":"5.6", "wspdi":"3.5","wgustm":"-9999.0", "wgusti":"-9999.0","wdird":"260","wdire":"West","vism":"-9999.0", "visi":"-9999.0","pressurem":"1014.3", "pressurei":"29.96","windchillm":"-999", "windchilli":"-999","heatindexm":"-9999", "heatindexi":"-9999","precipm":"-9999.00", "precipi":"-9999.00","conds":"Unknown","icon":"unknown","fog":"0","rain":"0","snow":"0","hail":"0","thunder":"0","tornado":"0","metar":"METAR CWTA 191600Z AUTO 26003KT 26/18 RMK AO1 SLP143 T02620175 58008" },
		{
		"date": {
		"pretty": "1:00 PM EDT on July 19, 2017",
		"year": "2017",
		"mon": "07",
		"mday": "19",
		"hour": "13",
		"min": "00",
		"tzname": "America/Montreal"
		},
		"utcdate": {
		"pretty": "5:00 PM GMT on July 19, 2017",
		"year": "2017",
		"mon": "07",
		"mday": "19",
		"hour": "17",
		"min": "00",
		"tzname": "UTC"
		},
		"tempm":"25.7", "tempi":"78.3","dewptm":"17.9", "dewpti":"64.2","hum":"62","wspdm":"5.6", "wspdi":"3.5","wgustm":"-9999.0", "wgusti":"-9999.0","wdird":"250","wdire":"WSW","vism":"-9999.0", "visi":"-9999.0","pressurem":"1014.4", "pressurei":"29.96","windchillm":"-999", "windchilli":"-999","heatindexm":"-9999", "heatindexi":"-9999","precipm":"-9999.00", "precipi":"-9999.00","conds":"Unknown","icon":"unknown","fog":"0","rain":"0","snow":"0","hail":"0","thunder":"0","tornado":"0","metar":"METAR CWTA 191700Z AUTO 25003KT 26/18 RMK AO1 SLP144 T02570179 55007" },
		{
		"date": {
		"pretty": "2:00 PM EDT on July 19, 2017",
		"year": "2017",
		"mon": "07",
		"mday": "19",
		"hour": "14",
		"min": "00",
		"tzname": "America/Montreal"
		},
		"utcdate": {
		"pretty": "6:00 PM GMT on July 19, 2017",
		"year": "2017",
		"mon": "07",
		"mday": "19",
		"hour": "18",
		"min": "00",
		"tzname": "UTC"
		},
		"tempm":"26", "tempi":"79","dewptm":"18", "dewpti":"65","hum":"53","wspdm":"5.6", "wspdi":"3.5","wgustm":"", "wgusti":"","wdird":"230","wdire":"SW","vism":"", "visi":"","pressurem":"1014", "pressurei":"29.94","windchillm":"-999", "windchilli":"-999","heatindexm":"-9999", "heatindexi":"-9999","precipm":"", "precipi":"","conds":"","icon":"","fog":"0","rain":"0","snow":"0","hail":"0","thunder":"0","tornado":"0","metar":"AAXX 19184 71612 16/// /2303 10260 20182 30052 40139 58007 60001 333 10269 20204 70000" },
		{
		"date": {
		"pretty": "4:00 PM EDT on July 19, 2017",
		"year": "2017",
		"mon": "07",
		"mday": "19",
		"hour": "16",
		"min": "00",
		"tzname": "America/Montreal"
		},
		"utcdate": {
		"pretty": "8:00 PM GMT on July 19, 2017",
		"year": "2017",
		"mon": "07",
		"mday": "19",
		"hour": "20",
		"min": "00",
		"tzname": "UTC"
		},
		"tempm":"26.2", "tempi":"79.2","dewptm":"18.6", "dewpti":"65.5","hum":"63","wspdm":"3.7", "wspdi":"2.3","wgustm":"-9999.0", "wgusti":"-9999.0","wdird":"200","wdire":"SSW","vism":"-9999.0", "visi":"-9999.0","pressurem":"1013.5", "pressurei":"29.93","windchillm":"-999", "windchilli":"-999","heatindexm":"-9999", "heatindexi":"-9999","precipm":"-9999.00", "precipi":"-9999.00","conds":"Unknown","icon":"unknown","fog":"0","rain":"0","snow":"0","hail":"0","thunder":"0","tornado":"0","metar":"METAR CWTA 192000Z AUTO 20002KT 26/19 RMK AO1 SLP135 T02620186 58009" },
		{
		"date": {
		"pretty": "5:00 PM EDT on July 19, 2017",
		"year": "2017",
		"mon": "07",
		"mday": "19",
		"hour": "17",
		"min": "00",
		"tzname": "America/Montreal"
		},
		"utcdate": {
		"pretty": "9:00 PM GMT on July 19, 2017",
		"year": "2017",
		"mon": "07",
		"mday": "19",
		"hour": "21",
		"min": "00",
		"tzname": "UTC"
		},
		"tempm":"26", "tempi":"79","dewptm":"19", "dewpti":"66","hum":"56","wspdm":"5.6", "wspdi":"3.5","wgustm":"", "wgusti":"","wdird":"210","wdire":"SSW","vism":"", "visi":"","pressurem":"1013", "pressurei":"29.91","windchillm":"-999", "windchilli":"-999","heatindexm":"-9999", "heatindexi":"-9999","precipm":"", "precipi":"","conds":"","icon":"","fog":"0","rain":"0","snow":"0","hail":"0","thunder":"0","tornado":"0","metar":"AAXX 19214 71612 26/// /2103 10261 20190 30042 40129 58010 333 60007" },
		{
		"date": {
		"pretty": "5:00 PM EDT on July 19, 2017",
		"year": "2017",
		"mon": "07",
		"mday": "19",
		"hour": "17",
		"min": "00",
		"tzname": "America/Montreal"
		},
		"utcdate": {
		"pretty": "9:00 PM GMT on July 19, 2017",
		"year": "2017",
		"mon": "07",
		"mday": "19",
		"hour": "21",
		"min": "00",
		"tzname": "UTC"
		},
		"tempm":"26.1", "tempi":"79.0","dewptm":"19.0", "dewpti":"66.2","hum":"65","wspdm":"5.6", "wspdi":"3.5","wgustm":"-9999.0", "wgusti":"-9999.0","wdird":"210","wdire":"SSW","vism":"-9999.0", "visi":"-9999.0","pressurem":"1012.9", "pressurei":"29.91","windchillm":"-999", "windchilli":"-999","heatindexm":"-9999", "heatindexi":"-9999","precipm":"-9999.00", "precipi":"-9999.00","conds":"Unknown","icon":"unknown","fog":"0","rain":"0","snow":"0","hail":"0","thunder":"0","tornado":"0","metar":"METAR CWTA 192100Z AUTO 21003KT 26/19 RMK AO1 SLP129 T02610190 58010" },
		{
		"date": {
		"pretty": "6:00 PM EDT on July 19, 2017",
		"year": "2017",
		"mon": "07",
		"mday": "19",
		"hour": "18",
		"min": "00",
		"tzname": "America/Montreal"
		},
		"utcdate": {
		"pretty": "10:00 PM GMT on July 19, 2017",
		"year": "2017",
		"mon": "07",
		"mday": "19",
		"hour": "22",
		"min": "00",
		"tzname": "UTC"
		},
		"tempm":"27.1", "tempi":"80.8","dewptm":"19.8", "dewpti":"67.6","hum":"64","wspdm":"3.7", "wspdi":"2.3","wgustm":"-9999.0", "wgusti":"-9999.0","wdird":"240","wdire":"WSW","vism":"-9999.0", "visi":"-9999.0","pressurem":"1012.7", "pressurei":"29.91","windchillm":"-999", "windchilli":"-999","heatindexm":"28.5", "heatindexi":"83.3","precipm":"-9999.00", "precipi":"-9999.00","conds":"Unknown","icon":"unknown","fog":"0","rain":"0","snow":"0","hail":"0","thunder":"0","tornado":"0","metar":"METAR CWTA 192200Z AUTO 24002KT 27/20 RMK AO1 SLP127 T02710198 56014" },
		{
		"date": {
		"pretty": "7:00 PM EDT on July 19, 2017",
		"year": "2017",
		"mon": "07",
		"mday": "19",
		"hour": "19",
		"min": "00",
		"tzname": "America/Montreal"
		},
		"utcdate": {
		"pretty": "11:00 PM GMT on July 19, 2017",
		"year": "2017",
		"mon": "07",
		"mday": "19",
		"hour": "23",
		"min": "00",
		"tzname": "UTC"
		},
		"tempm":"25.7", "tempi":"78.3","dewptm":"19.5", "dewpti":"67.1","hum":"68","wspdm":"3.7", "wspdi":"2.3","wgustm":"-9999.0", "wgusti":"-9999.0","wdird":"230","wdire":"SW","vism":"-9999.0", "visi":"-9999.0","pressurem":"1013.0", "pressurei":"29.92","windchillm":"-999", "windchilli":"-999","heatindexm":"-9999", "heatindexi":"-9999","precipm":"-9999.00", "precipi":"-9999.00","conds":"Unknown","icon":"unknown","fog":"0","rain":"0","snow":"0","hail":"0","thunder":"0","tornado":"0","metar":"METAR CWTA 192300Z AUTO 23002KT 26/20 RMK AO1 SLP130 T02570195 55005" },
		{
		"date": {
		"pretty": "8:00 PM EDT on July 19, 2017",
		"year": "2017",
		"mon": "07",
		"mday": "19",
		"hour": "20",
		"min": "00",
		"tzname": "America/Montreal"
		},
		"utcdate": {
		"pretty": "12:00 AM GMT on July 20, 2017",
		"year": "2017",
		"mon": "07",
		"mday": "20",
		"hour": "00",
		"min": "00",
		"tzname": "UTC"
		},
		"tempm":"23", "tempi":"74","dewptm":"20", "dewpti":"69","hum":"79","wspdm":"3.7", "wspdi":"2.3","wgustm":"", "wgusti":"","wdird":"270","wdire":"West","vism":"", "visi":"","pressurem":"1013", "pressurei":"29.91","windchillm":"-999", "windchilli":"-999","heatindexm":"-9999", "heatindexi":"-9999","precipm":"", "precipi":"","conds":"","icon":"","fog":"0","rain":"0","snow":"0","hail":"0","thunder":"0","tornado":"0","metar":"AAXX 20004 71612 16/// /2702 10232 20205 30042 40129 55000 60011 333 10272 20204 70013" },
		{
		"date": {
		"pretty": "8:00 PM EDT on July 19, 2017",
		"year": "2017",
		"mon": "07",
		"mday": "19",
		"hour": "20",
		"min": "00",
		"tzname": "America/Montreal"
		},
		"utcdate": {
		"pretty": "12:00 AM GMT on July 20, 2017",
		"year": "2017",
		"mon": "07",
		"mday": "20",
		"hour": "00",
		"min": "00",
		"tzname": "UTC"
		},
		"tempm":"23.2", "tempi":"73.8","dewptm":"19.5", "dewpti":"67.1","hum":"80","wspdm":"3.7", "wspdi":"2.3","wgustm":"-9999.0", "wgusti":"-9999.0","wdird":"270","wdire":"West","vism":"-9999.0", "visi":"-9999.0","pressurem":"1012.9", "pressurei":"29.91","windchillm":"-999", "windchilli":"-999","heatindexm":"-9999", "heatindexi":"-9999","precipm":"1.3", "precipi":"0.05","conds":"Unknown","icon":"unknown","fog":"0","rain":"0","snow":"0","hail":"0","thunder":"0","tornado":"0","metar":"METAR CWTA 200000Z AUTO 27002KT 23/20 RMK AO1 3PAST HR 5000 SLP129 P0005 T02320195 50013" },
		{
		"date": {
		"pretty": "9:00 PM EDT on July 19, 2017",
		"year": "2017",
		"mon": "07",
		"mday": "19",
		"hour": "21",
		"min": "00",
		"tzname": "America/Montreal"
		},
		"utcdate": {
		"pretty": "1:00 AM GMT on July 20, 2017",
		"year": "2017",
		"mon": "07",
		"mday": "20",
		"hour": "01",
		"min": "00",
		"tzname": "UTC"
		},
		"tempm":"22.0", "tempi":"71.6","dewptm":"20.9", "dewpti":"69.6","hum":"93","wspdm":"3.7", "wspdi":"2.3","wgustm":"-9999.0", "wgusti":"-9999.0","wdird":"290","wdire":"WNW","vism":"-9999.0", "visi":"-9999.0","pressurem":"1013.5", "pressurei":"29.93","windchillm":"-999", "windchilli":"-999","heatindexm":"-9999", "heatindexi":"-9999","precipm":"-9999.00", "precipi":"-9999.00","conds":"Unknown","icon":"unknown","fog":"0","rain":"0","snow":"0","hail":"0","thunder":"0","tornado":"0","metar":"METAR CWTA 200100Z AUTO 29002KT 22/21 RMK AO1 SLP135 T02200209 53008" },
		{
		"date": {
		"pretty": "10:00 PM EDT on July 19, 2017",
		"year": "2017",
		"mon": "07",
		"mday": "19",
		"hour": "22",
		"min": "00",
		"tzname": "America/Montreal"
		},
		"utcdate": {
		"pretty": "2:00 AM GMT on July 20, 2017",
		"year": "2017",
		"mon": "07",
		"mday": "20",
		"hour": "02",
		"min": "00",
		"tzname": "UTC"
		},
		"tempm":"22.4", "tempi":"72.3","dewptm":"21.2", "dewpti":"70.2","hum":"93","wspdm":"3.7", "wspdi":"2.3","wgustm":"-9999.0", "wgusti":"-9999.0","wdird":"280","wdire":"West","vism":"-9999.0", "visi":"-9999.0","pressurem":"1013.7", "pressurei":"29.94","windchillm":"-999", "windchilli":"-999","heatindexm":"-9999", "heatindexi":"-9999","precipm":"-9999.00", "precipi":"-9999.00","conds":"Unknown","icon":"unknown","fog":"0","rain":"0","snow":"0","hail":"0","thunder":"0","tornado":"0","metar":"METAR CWTA 200200Z AUTO 28002KT 22/21 RMK AO1 SLP137 T02240212 53007" },
		{
		"date": {
		"pretty": "11:00 PM EDT on July 19, 2017",
		"year": "2017",
		"mon": "07",
		"mday": "19",
		"hour": "23",
		"min": "00",
		"tzname": "America/Montreal"
		},
		"utcdate": {
		"pretty": "3:00 AM GMT on July 20, 2017",
		"year": "2017",
		"mon": "07",
		"mday": "20",
		"hour": "03",
		"min": "00",
		"tzname": "UTC"
		},
		"tempm":"22", "tempi":"72","dewptm":"20", "dewpti":"68","hum":"83","wspdm":"5.6", "wspdi":"3.5","wgustm":"", "wgusti":"","wdird":"310","wdire":"NW","vism":"", "visi":"","pressurem":"1014", "pressurei":"29.94","windchillm":"-999", "windchilli":"-999","heatindexm":"-9999", "heatindexi":"-9999","precipm":"", "precipi":"","conds":"","icon":"","fog":"0","rain":"0","snow":"0","hail":"0","thunder":"0","tornado":"0","metar":"AAXX 20034 71612 26/// /3103 10224 20199 30049 40136 50007 333 60007" },
		{
		"date": {
		"pretty": "11:00 PM EDT on July 19, 2017",
		"year": "2017",
		"mon": "07",
		"mday": "19",
		"hour": "23",
		"min": "00",
		"tzname": "America/Montreal"
		},
		"utcdate": {
		"pretty": "3:00 AM GMT on July 20, 2017",
		"year": "2017",
		"mon": "07",
		"mday": "20",
		"hour": "03",
		"min": "00",
		"tzname": "UTC"
		},
		"tempm":"22.4", "tempi":"72.3","dewptm":"19.9", "dewpti":"67.8","hum":"86","wspdm":"5.6", "wspdi":"3.5","wgustm":"-9999.0", "wgusti":"-9999.0","wdird":"310","wdire":"NW","vism":"-9999.0", "visi":"-9999.0","pressurem":"1013.6", "pressurei":"29.94","windchillm":"-999", "windchilli":"-999","heatindexm":"-9999", "heatindexi":"-9999","precipm":"-9999.00", "precipi":"-9999.00","conds":"Unknown","icon":"unknown","fog":"0","rain":"0","snow":"0","hail":"0","thunder":"0","tornado":"0","metar":"METAR CWTA 200300Z AUTO 31003KT 22/20 RMK AO1 SLP136 T02240199 50007" }
		],
		"dailysummary": [
		{ "date": {
		"pretty": "12:00 AM EDT on July 19, 2017",
		"year": "2017",
		"mon": "07",
		"mday": "19",
		"hour": "00",
		"min": "00",
		"tzname": "America/Montreal"
		},
		"fog":"0","rain":"0","snow":"0","snowfallm":"", "snowfalli":"","monthtodatesnowfallm":"", "monthtodatesnowfalli":"","since1julsnowfallm":"", "since1julsnowfalli":"","snowdepthm":"", "snowdepthi":"","hail":"0","thunder":"0","tornado":"0","meantempm":"24", "meantempi":"74","meandewptm":"18", "meandewpti":"65","meanpressurem":"1014.34", "meanpressurei":"29.95","meanwindspdm":"4", "meanwindspdi":"3","meanwdire":"WSW","meanwdird":"242","meanvism":"", "meanvisi":"","humidity":"72","maxtempm":"27", "maxtempi":"81","mintempm":"20", "mintempi":"68","maxhumidity":"93","minhumidity":"53","maxdewptm":"21", "maxdewpti":"70","mindewptm":"17", "mindewpti":"62","maxpressurem":"1016", "maxpressurei":"30.01","minpressurem":"1013", "minpressurei":"29.91","maxwspdm":"7", "maxwspdi":"5","minwspdm":"2", "minwspdi":"1","maxvism":"", "maxvisi":"","minvism":"", "minvisi":"","gdegreedays":"24","heatingdegreedays":"0","coolingdegreedays":"10","precipm":"1.0", "precipi":"0.04","precipsource":"Precip6GroupSynop","heatingdegreedaysnormal":"","monthtodateheatingdegreedays":"","monthtodateheatingdegreedaysnormal":"","since1sepheatingdegreedays":"","since1sepheatingdegreedaysnormal":"","since1julheatingdegreedays":"","since1julheatingdegreedaysnormal":"","coolingdegreedaysnormal":"","monthtodatecoolingdegreedays":"","monthtodatecoolingdegreedaysnormal":"","since1sepcoolingdegreedays":"","since1sepcoolingdegreedaysnormal":"","since1jancoolingdegreedays":"","since1jancoolingdegreedaysnormal":"" }
		]
	}
}
